{
    "version": "2.49.0",
    "description": "End-to-End encrypted and anonymous Internet",
    "homepage": "https://i2pd.website",
    "license": "BSD-3-Clause",
    "architecture": {
        "64bit": {
            "url": "https://github.com/PurpleI2P/i2pd/releases/download/2.49.0/i2pd_2.49.0_win64_mingw.zip",
            "hash": "sha512:cd9f656bab9e8902ff51e3609bc767690064842c5ce6bdf37fa27cd149374624486c9aa59dd3d5c1b70f03ae441e1053d8724d19860b0bb0e83175aa0a709d82"
        },
        "32bit": {
            "url": "https://github.com/PurpleI2P/i2pd/releases/download/2.49.0/i2pd_2.49.0_win32_mingw.zip",
            "hash": "sha512:0491b07ca4d3504d208a48ee2510a8e8443ba960a25d0924e661b34f428f1b1d3d176a7d02393bda639cf089d7b537f681cb86c01c31a09462e0f6349c4a9457"
        }
    },
    "pre_install": [
        "Move-Item \"$dir\\contrib\\*\" \"$dir\"",
        "Remove-Item \"$dir\\contrib\"",
        "foreach ($name in @('irc-keys.dat', 'ntcp2.keys', 'router.info', 'router.keys')) {",
        "    if (!(Test-Path \"$persist_dir\\$name\")) { New-Item \"$dir\\$name\" | Out-Null }",
        "}"
    ],
    "bin": "i2pd.exe",
    "shortcuts": [
        [
            "i2pd.exe",
            "I2Pd"
        ]
    ],
    "persist": [
        "addressbook",
        "destinations",
        "netDb",
        "peerProfiles",
        "tags",
        "irc-keys.dat",
        "ntcp2.keys",
        "router.info",
        "router.keys",
        "certificates",
        "tunnels.d",
        "i2pd.conf",
        "tunnels.conf"
    ],
    "checkver": {
        "github": "https://github.com/PurpleI2P/i2pd"
    },
    "autoupdate": {
        "architecture": {
            "64bit": {
                "url": "https://github.com/PurpleI2P/i2pd/releases/download/$version/i2pd_$version_win64_mingw.zip"
            },
            "32bit": {
                "url": "https://github.com/PurpleI2P/i2pd/releases/download/$version/i2pd_$version_win32_mingw.zip"
            }
        },
        "hash": {
            "url": "$baseurl/SHA512SUMS"
        }
    }
}
